LICENSE.txt
MANIFEST.in
README.md
requirements.txt
setup.cfg
setup.py
mliamlib.egg-info/PKG-INFO
mliamlib.egg-info/SOURCES.txt
mliamlib.egg-info/dependency_links.txt
mliamlib.egg-info/requires.txt
mliamlib.egg-info/top_level.txt
mlib/HDF5.py
mlib/IDL.py
mlib/__init__.py
mlib/_doctest.py
mlib/classification.py
mlib/cluster.py
mlib/color.py
mlib/correlation.py
mlib/datadict.py
mlib/dimension_reduction.py
mlib/equation.py
mlib/flatfile.py
mlib/formatting.py
mlib/iterable.py
mlib/latlon.py
mlib/log.py
mlib/memory.py
mlib/mstring.py
mlib/mtime.py
mlib/mtypes.py
mlib/numeric.py
mlib/plot.py
mlib/plot3d.py
mlib/plot_seaborn.py
mlib/progressbar.py
mlib/regex.py
mlib/regression.py
mlib/shell.py
mlib/spanning.py