Metadata-Version: 1.1
Name: mliamlib
Version: 1.0.7
Summary: Various helper functions for python usage 
Home-page: https://github.com/JPLMLIA/MLIB
Author: Lukas Mandrake
Author-email: lukas.mandrake@jpl.caltech.edu
License: MIT
Download-URL: https://github.com/JPLMLIA/MLIB/archive/1.0.0.tar.gz
Platform: UNKNOWN
Classifier: Development Status :: 3 - Alpha
Classifier: Intended Audience :: Science/Research
Classifier: Intended Audience :: Education
Classifier: Natural Language :: English
Classifier: Operating System :: POSIX :: Linux
Classifier: Programming Language :: Python :: 3.6
Classifier: Topic :: Utilities
